lmi_sdp/__init__.py
lmi_sdp/lm.py
lmi_sdp/lmi.py
lmi_sdp/sdp.py
PyLMI_SDP-1.1.1.dist-info/LICENSE.txt
PyLMI_SDP-1.1.1.dist-info/METADATA
PyLMI_SDP-1.1.1.dist-info/WHEEL
PyLMI_SDP-1.1.1.dist-info/top_level.txt
PyLMI_SDP-1.1.1.dist-info/RECORD
