Metadata-Version: 2.1
Name: PyLMI-SDP
Version: 1.1.1
Summary: Symbolic linear matrix inequalities (LMI) and semi-definite programming (SDP) tools for Python
Home-page: http://github.com/cdsousa/PyLMI-SDP
Author: Cristovao D. Sousa
Author-email: crisjss@gmail.com
License: BSD
Keywords: LMI SDP
Classifier: Development Status :: 4 - Beta
Classifier: License :: OSI Approved :: BSD License
Classifier: Operating System :: OS Independent
Classifier: Programming Language :: Python
Classifier: Intended Audience :: Developers
Classifier: Intended Audience :: Education
Classifier: Intended Audience :: Manufacturing
Classifier: Intended Audience :: Science/Research
License-File: LICENSE.txt
